setup.py
darea/__init__.py
darea.egg-info/PKG-INFO
darea.egg-info/SOURCES.txt
darea.egg-info/dependency_links.txt
darea.egg-info/top_level.txt