Metadata-Version: 1.0
Name: darea
Version: 0.1.0
Summary: this darea helps in finding area and perimeter of 2D and 3D figures
Home-page: UNKNOWN
Author: Atul gupta
Author-email: atulg9927@gmail.com
License: MIT
Keywords: area,2D surface,3D surface
Platform: UNKNOWN
